MANIFEST.in
README.rst
setup.py
ckanext/__init__.py
ckanext/related_datasets/__init__.py
ckanext/related_datasets/plugin.py
ckanext/related_datasets/controllers/__init__.py
ckanext/related_datasets/controllers/related_datasets_controller.py
ckanext/related_datasets/tests/__init__.py
ckanext/related_datasets/tests/test_plugin.py
ckanext_related_datasets.egg-info/PKG-INFO
ckanext_related_datasets.egg-info/SOURCES.txt
ckanext_related_datasets.egg-info/dependency_links.txt
ckanext_related_datasets.egg-info/entry_points.txt
ckanext_related_datasets.egg-info/top_level.txt