Metadata-Version: 1.1
Name: ckanext-related-datasets
Version: 0.0.1
Summary: Link back to related datasets across the internet on your CKAN installation
Home-page: https://github.com/exversion/ckanext-related-datasets
Author: Exversion
Author-email: ckan@exversion.com
License: AGPL
Keywords: CKAN datasets network socrata
Platform: UNKNOWN
Classifier: Development Status :: 4 - Beta
Classifier: License :: OSI Approved :: GNU Affero General Public License v3 or later (AGPLv3+)
Classifier: Programming Language :: Python :: 2.6
Classifier: Programming Language :: Python :: 2.7
